lab04-Quadrature Decoder on ICE40/QuadDecoder.v
module QuadDecoder (
    input clk,
    input A,
    input B,
    input rst,

    output reg signed [31:0] count,
    output reg dir
);

    localparam S00 = 2'b00,
               S01 = 2'b01,
               S10 = 2'b10,
               S11 = 2'b11;

    reg [1:0] state = S00;
    reg [1:0] sync = 2'b00;
    reg [1:0] AB = 2'b00;

    // Two-stage input synchronizer (A and B are in a different clock domain)
    always @(posedge clk) begin
        sync <= {A, B};
        AB <= sync;
    end

    // State machine: direction and count update
    always @(posedge clk) begin
        if (rst) begin
            count <= 0;
            state <= S00;
            dir <= 1'b0;
        end else begin
            case (state)
                S00: begin
                    if (AB == 2'b01) begin
                        count <= count - 1;
                        state <= S01;
                        dir <= 1'b0;
                    end
                    else if (AB == 2'b10) begin
                        count <= count + 1;
                        state <= S10;
                        dir <= 1'b1;
                    end
                end
                S01: begin
                    if (AB == 2'b00) begin
                        count <= count + 1;
                        state <= S00;
                        dir <= 1'b1;
                    end
                    else if (AB == 2'b11) begin
                        count <= count - 1;
                        state <= S11;
                        dir <= 1'b0;
                    end
                end
                S10: begin
                    if (AB == 2'b00) begin
                        count <= count - 1;
                        state <= S00;
                        dir <= 1'b0;
                    end
                    else if (AB == 2'b11) begin
                        count <= count + 1;
                        state <= S11;
                        dir <= 1'b1;
                    end
                end
                S11: begin
                    if (AB == 2'b01) begin
                        count <= count + 1;
                        state <= S01;
                        dir <= 1'b1;
                    end
                    else if (AB == 2'b10) begin
                        count <= count - 1;
                        state <= S10;
                        dir <= 1'b0;
                    end
                end
            endcase
        end
    end

endmodule

lab04-Quadrature Decoder on ICE40/QuadDecoder_tb.v
`include "QuadDecoder.v"
`timescale 1ns / 1ps
module QuadDecoder_tb;
  reg clk, A, B, rst;
  wire signed [31:0] count;
  wire dir;

  QuadDecoder dut (
      .clk (clk),
      .A(A),
      .B(B),
      .rst(rst),
      .count(count),
      .dir(dir)
  );

  // generate clock signal
  initial begin
    forever begin
      clk = 0;
      #1;
      clk = ~clk;
      #1;
    end
  end

// Start of your testbench script
  initial begin
    $dumpfile("quad_signals.vcd");
    $dumpvars(0, QuadDecoder_tb);

    // initial values
    A = 0;
    B = 0;
    rst = 1;
    // hold reset
    #10;
    rst = 0;

    // forward: 00 -> 10 -> 11 -> 01 -> 00
    #10; A = 1; B = 0;
    #10; A = 1; B = 1;
    #10; A = 0; B = 1;
    #10; A = 0; B = 0;

    // reverse: 00 -> 01 -> 11 -> 10 -> 00
    #10; A = 0; B = 1;
    #10; A = 1; B = 1;
    #10; A = 1; B = 0;
    #10; A = 0; B = 0;

    // reverse: 00 -> 01 -> 11 -> 10 -> 00
    #10; A = 0; B = 1;
    #10; A = 1; B = 1;
    #10; A = 1; B = 0;
    #10; A = 0; B = 0;

    // forward: 00 -> 10 -> 11 -> 01 -> 00
    #10; A = 1; B = 0;
    #10; A = 1; B = 1;
    #10; A = 0; B = 1;
    #10; A = 0; B = 0;

    #10;
    $finish;
  end
endmodule

lab04-Quadrature Decoder on ICE40/quad_signals.vcd
$date
	Wed Apr 29 20:42:22 2026
$end
$version
	Icarus Verilog
$end
$timescale
	1ps
$end
$scope module QuadDecoder_tb $end
$var wire 1 ! dir $end
$var wire 32 " count [31:0] $end
$var reg 1 # A $end
$var reg 1 $ B $end
$var reg 1 % clk $end
$var reg 1 & rst $end
$scope module dut $end
$var wire 1 # A $end
$var wire 1 $ B $end
$var wire 1 % clk $end
$var wire 1 & rst $end
$var parameter 2 ' S00 $end
$var parameter 2 ( S01 $end
$var parameter 2 ) S10 $end
$var parameter 2 * S11 $end
$var reg 2 + AB [1:0] $end
$var reg 32 , count [31:0] $end
$var reg 1 ! dir $end
$var reg 2 - state [1:0] $end
$var reg 2 . sync [1:0] $end
$upscope $end
$upscope $end
$enddefinitions $end
$comment Show the parameter values. $end
$dumpall
b11 *
b10 )
b1 (
b0 '
$end
#0
$dumpvars
b0 .
b0 -
bx ,
b0 +
1&
0%
0$
0#
bx "
x!
$end
#1000
0!
b0 "
b0 ,
1%
#2000
0%
#3000
1%
#4000
0%
#5000
1%
#6000
0%
#7000
1%
#8000
0%
#9000
1%
#10000
0%
0&
#11000
1%
#12000
0%
#13000
1%
#14000
0%
#15000
1%
#16000
0%
#17000
1%
#18000
0%
#19000
1%
#20000
0%
1#
#21000
b10 .
1%
#22000
0%
#23000
b10 +
1%
#24000
0%
#25000
1!
b10 -
b1 "
b1 ,
1%
#26000
0%
#27000
1%
#28000
0%
#29000
1%
#30000
0%
1$
#31000
b11 .
1%
#32000
0%
#33000
b11 +
1%
#34000
0%
#35000
b11 -
b10 "
b10 ,
1%
#36000
0%
#37000
1%
#38000
0%
#39000
1%
#40000
0%
0#
#41000
b1 .
1%
#42000
0%
#43000
b1 +
1%
#44000
0%
#45000
b1 -
b11 "
b11 ,
1%
#46000
0%
#47000
1%
#48000
0%
#49000
1%
#50000
0%
0$
#51000
b0 .
1%
#52000
0%
#53000
b0 +
1%
#54000
0%
#55000
b0 -
b100 "
b100 ,
1%
#56000
0%
#57000
1%
#58000
0%
#59000
1%
#60000
0%
1$
#61000
b1 .
1%
#62000
0%
#63000
b1 +
1%
#64000
0%
#65000
0!
b1 -
b11 "
b11 ,
1%
#66000
0%
#67000
1%
#68000
0%
#69000
1%
#70000
0%
1#
#71000
b11 .
1%
#72000
0%
#73000
b11 +
1%
#74000
0%
#75000
b11 -
b10 "
b10 ,
1%
#76000
0%
#77000
1%
#78000
0%
#79000
1%
#80000
0%
0$
#81000
b10 .
1%
#82000
0%
#83000
b10 +
1%
#84000
0%
#85000
b10 -
b1 "
b1 ,
1%
#86000
0%
#87000
1%
#88000
0%
#89000
1%
#90000
0%
0#
#91000
b0 .
1%
#92000
0%
#93000
b0 +
1%
#94000
0%
#95000
b0 -
b0 "
b0 ,
1%
#96000
0%
#97000
1%
#98000
0%
#99000
1%
#100000
0%
1$
#101000
b1 .
1%
#102000
0%
#103000
b1 +
1%
#104000
0%
#105000
b1 -
b11111111111111111111111111111111 "
b11111111111111111111111111111111 ,
1%
#106000
0%
#107000
1%
#108000
0%
#109000
1%
#110000
0%
1#
#111000
b11 .
1%
#112000
0%
#113000
b11 +
1%
#114000
0%
#115000
b11 -
b11111111111111111111111111111110 "
b11111111111111111111111111111110 ,
1%
#116000
0%
#117000
1%
#118000
0%
#119000
1%
#120000
0%
0$
#121000
b10 .
1%
#122000
0%
#123000
b10 +
1%
#124000
0%
#125000
b10 -
b11111111111111111111111111111101 "
b11111111111111111111111111111101 ,
1%
#126000
0%
#127000
1%
#128000
0%
#129000
1%
#130000
0%
0#
#131000
b0 .
1%
#132000
0%
#133000
b0 +
1%
#134000
0%
#135000
b0 -
b11111111111111111111111111111100 "
b11111111111111111111111111111100 ,
1%
#136000
0%
#137000
1%
#138000
0%
#139000
1%
#140000
0%
1#
#141000
b10 .
1%
#142000
0%
#143000
b10 +
1%
#144000
0%
#145000
1!
b10 -
b11111111111111111111111111111101 "
b11111111111111111111111111111101 ,
1%
#146000
0%
#147000
1%
#148000
0%
#149000
1%
#150000
0%
1$
#151000
b11 .
1%
#152000
0%
#153000
b11 +
1%
#154000
0%
#155000
b11 -
b11111111111111111111111111111110 "
b11111111111111111111111111111110 ,
1%
#156000
0%
#157000
1%
#158000
0%
#159000
1%
#160000
0%
0#
#161000
b1 .
1%
#162000
0%
#163000
b1 +
1%
#164000
0%
#165000
b1 -
b11111111111111111111111111111111 "
b11111111111111111111111111111111 ,
1%
#166000
0%
#167000
1%
#168000
0%
#169000
1%
#170000
0%
0$
#171000
b0 .
1%
#172000
0%
#173000
b0 +
1%
#174000
0%
#175000
b0 -
b0 "
b0 ,
1%
