lab09-PWM_IP/PWM.v
`timescale 1 ps / 1 ps

module PWM #(
    parameter CLK_FREQ = 50000000,
    parameter PWM_FREQ = 20000
) (
    input  wire        clk,
    input  wire        rst,
    input  wire        enable,
    input  wire        dir,
    input  wire [31:0] duty,

    output reg         INA,
    output reg         INB,
    output reg         C // ie PWM
);
    // 2500 ticks for one period for the above values BE CAREFUL not higher!
    localparam PWM_PERIOD = CLK_FREQ / PWM_FREQ; 

    reg [31:0] counter;

    // Counts one full PWM period, then starts again from zero.
    always @(posedge clk or posedge rst) begin
        if (rst) begin
            counter <= 32'd0;
        end else begin
            if (counter >= PWM_PERIOD - 1) begin
                counter <= 32'd0;
            end else begin
                counter <= counter + 1'b1;
            end
        end
    end

    // INA and INB set the motor direction, C is the PWM speed signal.
    always @(posedge clk or posedge rst) begin
        if (rst) begin
            INA <= 1'b0;
            INB <= 1'b0;
            C   <= 1'b0;
        end else begin
            if (enable) begin
                // dir = 0 gives one direction, dir = 1 gives the other.
                INA <= ~dir;
                INB <= dir;
                // C stays high until the counter reaches the duty value.
                C   <= (counter < duty);
            end else begin
                // Safe stop state when the module is disabled.
                INA <= 1'b0;
                INB <= 1'b0;
                C   <= 1'b0;
            end
        end
    end

endmodule

lab09-PWM_IP/PWM_tb.v
`timescale 1 ns / 1 ps

module PWM_tb;

    reg clk;
    reg rst;
    reg enable;
    reg dir;
    reg [31:0] duty;

    wire INA;
    wire INB;
    wire C;

    initial begin
        $dumpfile("lab09-PWM_IP/PWM_tb.vcd");
        $dumpvars(0, PWM_tb);
    end

    // Smaller values make the simulation easier to read.
    PWM #(
        .CLK_FREQ(100),
        .PWM_FREQ(10)
    ) dut (
        .clk(clk),
        .rst(rst),
        .enable(enable),
        .dir(dir),
        .duty(duty),
        .INA(INA),
        .INB(INB),
        .C(C)
    );

    initial begin
        clk = 1'b0;
        forever #5 clk = ~clk;
    end

    initial begin
        rst    = 1'b1;
        enable = 1'b0;
        dir    = 1'b0;
        duty   = 32'd0;

        #30;
        rst = 1'b0;

        // Disabled: all outputs should stay low.
        #50;

        // One direction, 50 percent duty cycle.
        enable = 1'b1;
        dir    = 1'b0;
        duty   = 32'd5;
        #150;

        // Same direction, smaller duty cycle.
        duty = 32'd2;
        #150;

        // Reverse direction, same PWM duty.
        dir = 1'b1;
        #150;

        // Stop again.
        enable = 1'b0;
        #50;

        $finish;
    end

endmodule

lab09-PWM_IP/PWM_tb.vcd
$date
	Sun May 10 18:33:31 2026
$end
$version
	Icarus Verilog
$end
$timescale
	1ps
$end
$scope module PWM_tb $end
$var wire 1 ! INB $end
$var wire 1 " INA $end
$var wire 1 # C $end
$var reg 1 $ clk $end
$var reg 1 % dir $end
$var reg 32 & duty [31:0] $end
$var reg 1 ' enable $end
$var reg 1 ( rst $end
$scope module dut $end
$var wire 1 $ clk $end
$var wire 1 % dir $end
$var wire 32 ) duty [31:0] $end
$var wire 1 ' enable $end
$var wire 1 ( rst $end
$var parameter 32 * CLK_FREQ $end
$var parameter 32 + PWM_FREQ $end
$var parameter 32 , PWM_PERIOD $end
$var reg 1 # C $end
$var reg 1 " INA $end
$var reg 1 ! INB $end
$var reg 32 - counter [31:0] $end
$upscope $end
$upscope $end
$enddefinitions $end
$comment Show the parameter values. $end
$dumpall
b1010 ,
b1010 +
b1100100 *
$end
#0
$dumpvars
b0 -
b0 )
1(
0'
b0 &
0%
0$
0#
0"
0!
$end
#5000
1$
#10000
0$
#15000
1$
#20000
0$
#25000
1$
#30000
0$
0(
#35000
b1 -
1$
#40000
0$
#45000
b10 -
1$
#50000
0$
#55000
b11 -
1$
#60000
0$
#65000
b100 -
1$
#70000
0$
#75000
b101 -
1$
#80000
0$
b101 &
b101 )
1'
#85000
1"
b110 -
1$
#90000
0$
#95000
b111 -
1$
#100000
0$
#105000
b1000 -
1$
#110000
0$
#115000
b1001 -
1$
#120000
0$
#125000
b0 -
1$
#130000
0$
#135000
b1 -
1#
1$
#140000
0$
#145000
b10 -
1$
#150000
0$
#155000
b11 -
1$
#160000
0$
#165000
b100 -
1$
#170000
0$
#175000
b101 -
1$
#180000
0$
#185000
0#
b110 -
1$
#190000
0$
#195000
b111 -
1$
#200000
0$
#205000
b1000 -
1$
#210000
0$
#215000
b1001 -
1$
#220000
0$
#225000
b0 -
1$
#230000
0$
b10 &
b10 )
#235000
b1 -
1#
1$
#240000
0$
#245000
b10 -
1$
#250000
0$
#255000
b11 -
0#
1$
#260000
0$
#265000
b100 -
1$
#270000
0$
#275000
b101 -
1$
#280000
0$
#285000
b110 -
1$
#290000
0$
#295000
b111 -
1$
#300000
0$
#305000
b1000 -
1$
#310000
0$
#315000
b1001 -
1$
#320000
0$
#325000
b0 -
1$
#330000
0$
#335000
b1 -
1#
1$
#340000
0$
#345000
b10 -
1$
#350000
0$
#355000
b11 -
0#
1$
#360000
0$
#365000
b100 -
1$
#370000
0$
#375000
b101 -
1$
#380000
0$
1%
#385000
1!
0"
b110 -
1$
#390000
0$
#395000
b111 -
1$
#400000
0$
#405000
b1000 -
1$
#410000
0$
#415000
b1001 -
1$
#420000
0$
#425000
b0 -
1$
#430000
0$
#435000
b1 -
1#
1$
#440000
0$
#445000
b10 -
1$
#450000
0$
#455000
b11 -
0#
1$
#460000
0$
#465000
b100 -
1$
#470000
0$
#475000
b101 -
1$
#480000
0$
#485000
b110 -
1$
#490000
0$
#495000
b111 -
1$
#500000
0$
#505000
b1000 -
1$
#510000
0$
#515000
b1001 -
1$
#520000
0$
#525000
b0 -
1$
#530000
0$
0'
#535000
b1 -
0!
1$
#540000
0$
#545000
b10 -
1$
#550000
0$
#555000
b11 -
1$
#560000
0$
#565000
b100 -
1$
#570000
0$
#575000
b101 -
1$
