lab13-20simcontroller/RPI-controller/verilog/PWM.v
`timescale 1 ps / 1 ps

module PWM #(
    parameter CLK_FREQ = 50000000,
    parameter PWM_FREQ = 20000
) (
    input  wire        clk,
    input  wire        rst,
    input  wire        enable,
    input  wire        dir,
    input  wire [13:0] duty,

    output reg         INA,
    output reg         INB,
    output reg         C // ie PWM
);
    // 2500 ticks for one period for the above values BE CAREFUL not higher!
    localparam PWM_PERIOD = CLK_FREQ / PWM_FREQ;

    reg [13:0] counter;

    // Counts one full PWM period, then starts again from zero.
    always @(posedge clk or posedge rst) begin
        if (rst) begin
            counter <= 14'd0;
        end else begin
            if (counter >= PWM_PERIOD - 1) begin
                counter <= 14'd0;
            end else begin
                counter <= counter + 1'b1;
            end
        end
    end

    // INA and INB set the motor direction, C is the PWM speed signal.
    always @(posedge clk or posedge rst) begin
        if (rst) begin
            INA <= 1'b0;
            INB <= 1'b0;
            C   <= 1'b0;
        end else begin
            if (enable) begin
                // dir = 0 gives one direction, dir = 1 gives the other.
                INA <= ~dir;
                INB <= dir;
                // C stays high until the counter reaches the duty value.
                C   <= (counter < duty);
            end else begin
                // Safe stop state when the module is disabled.
                INA <= 1'b0;
                INB <= 1'b0;
                C   <= 1'b0;
            end
        end
    end

endmodule

lab13-20simcontroller/RPI-controller/verilog/QuadDecoder.v
module QuadDecoder (
    input clk,
    input A,
    input B,
    input rst,

    output reg signed [15:0] count
);

    localparam S00 = 2'b00,
               S01 = 2'b01,
               S10 = 2'b10,
               S11 = 2'b11;

    reg [1:0] state = S00;
    reg [1:0] sync = 2'b00;
    reg [1:0] AB = 2'b00;

    // Two-stage input synchronizer (A and B are in a different clock domain)
    always @(posedge clk) begin
        sync <= {A, B};
        AB <= sync;
    end

    // State machine: direction and count update
    always @(posedge clk) begin
        if (rst) begin
            count <= 0;
            state <= S00;
            dir <= 1'b0;
        end else begin
            case (state)
                S00: begin
                    if (AB == 2'b01) begin
                        count <= count - 1;
                        state <= S01;
                        dir <= 1'b0;
                    end
                    else if (AB == 2'b10) begin
                        count <= count + 1;
                        state <= S10;
                        dir <= 1'b1;
                    end
                end
                S01: begin
                    if (AB == 2'b00) begin
                        count <= count + 1;
                        state <= S00;
                        dir <= 1'b1;
                    end
                    else if (AB == 2'b11) begin
                        count <= count - 1;
                        state <= S11;
                        dir <= 1'b0;
                    end
                end
                S10: begin
                    if (AB == 2'b00) begin
                        count <= count - 1;
                        state <= S00;
                        dir <= 1'b0;
                    end
                    else if (AB == 2'b11) begin
                        count <= count + 1;
                        state <= S11;
                        dir <= 1'b1;
                    end
                end
                S11: begin
                    if (AB == 2'b01) begin
                        count <= count + 1;
                        state <= S01;
                        dir <= 1'b1;
                    end
                    else if (AB == 2'b10) begin
                        count <= count - 1;
                        state <= S10;
                        dir <= 1'b0;
                    end
                end
            endcase
        end
    end

endmodule

lab13-20simcontroller/RPI-controller/verilog/SPI.v
module SPI (
    input  wire        clk,
    input  wire        rst,
    input  wire        spi_clk,
    input  wire        spi_pico,
    input  wire        spi_cs,

    input  wire signed [15:0] pitch_encoder_count,
    input  wire signed [15:0] yaw_encoder_count,

    output wire [13:0] pitch_pwm_duty,
    output wire        pitch_dir,
    output wire        pitch_pwm_enable,

    output wire [13:0] yaw_pwm_duty,
    output wire        yaw_dir,
    output wire        yaw_pwm_enable,

    output wire        spi_poci
);

  /*
   * 32-bit full-duplex SPI frame, mode 0
   *
   * Raspberry Pi -> FPGA:
   *   [31:16] yaw   : bit15 dir, bit14 enable, bit13:0 PWM
   *   [15:0]  pitch : bit15 dir, bit14 enable, bit13:0 PWM
   *
   * FPGA -> Raspberry Pi:
   *   [31:16] signed yaw encoder count
   *   [15:0]  signed pitch encoder count
   */

  reg [31:0] rx_shift = 32'd0;
  reg [31:0] tx_shift = 32'd0;
  reg [5:0]  bit_count = 6'd0;

  reg [13:0] pitch_pwm_duty_r   = 14'd0;
  reg        pitch_dir_r        = 1'b0;
  reg        pitch_pwm_enable_r = 1'b0;

  reg [13:0] yaw_pwm_duty_r     = 14'd0;
  reg        yaw_dir_r          = 1'b0;
  reg        yaw_pwm_enable_r   = 1'b0;

  assign pitch_pwm_duty   = pitch_pwm_duty_r;
  assign pitch_dir        = pitch_dir_r;
  assign pitch_pwm_enable = pitch_pwm_enable_r;

  assign yaw_pwm_duty     = yaw_pwm_duty_r;
  assign yaw_dir          = yaw_dir_r;
  assign yaw_pwm_enable   = yaw_pwm_enable_r;

  assign spi_poci = tx_shift[31];

  // Start of SPI frame: preload encoder snapshot for MISO
  always @(negedge spi_cs or posedge rst) begin
    if (rst) begin
      tx_shift  <= 0;
      rx_shift  <= 0;
      bit_count <= 0;
    end else begin
      tx_shift  <= {yaw_encoder_count, pitch_encoder_count};
      rx_shift  <= 0;
      bit_count <= 0;
    end
  end

  // Sample MOSI on rising edge (mode 0)
  always @(posedge spi_clk or posedge rst) begin
    if (rst) begin
      rx_shift  <= 0;
      bit_count <= 0;
    end else if (!spi_cs) begin
      rx_shift <= {rx_shift[30:0], spi_pico};
      if (bit_count < 32)
        bit_count <= bit_count + 1;
    end
  end

  // Shift MISO on falling edge so next bit is ready before next rising edge
  always @(negedge spi_clk or posedge rst) begin
    if (rst) begin
      tx_shift <= 0;
    end else if (!spi_cs) begin
      tx_shift <= {tx_shift[30:0], 1'b0};
    end
  end

  // Accept command only if exactly 32 bits were received
  always @(posedge spi_cs or posedge rst) begin
    if (rst) begin
      yaw_pwm_duty_r      <= 0;
      yaw_dir_r           <= 0;
      yaw_pwm_enable_r    <= 0;
      pitch_pwm_duty_r    <= 0;
      pitch_dir_r         <= 0;
      pitch_pwm_enable_r  <= 0;
    end else if (bit_count == 32) begin
      yaw_dir_r           <= rx_shift[31];
      yaw_pwm_enable_r    <= rx_shift[30];
      yaw_pwm_duty_r      <= rx_shift[29:16];

      pitch_dir_r         <= rx_shift[15];
      pitch_pwm_enable_r  <= rx_shift[14];
      pitch_pwm_duty_r    <= rx_shift[13:0];
    end
  end

endmodule

lab13-20simcontroller/RPI-controller/verilog/TopEntity.v
module TopEntity (
    input  clk,
    input  btn1,        // reset button

    input  SPI_CLK,
    input  SPI_PICO,
    input  SPI_CS,

    input  PITCH_ENC_A,
    input  PITCH_ENC_B,

    input YAW_ENC_A,
    input YAW_ENC_B,

    output PITCH_DIRA,
    output PITCH_PWM_VAL,
    output PITCH_DIRB,

    output YAW_DIRA,
    output YAW_PWM_VAL,
    output YAW_DIRB,

    output SPI_POCI
);

  wire signed [15:0] pitch_count;
  wire [13:0]        pitch_pwm_duty;
  wire               pitch_dir;
  wire               pitch_pwm_enable;

  wire signed [15:0] yaw_count;
  wire [13:0]        yaw_pwm_duty;
  wire               yaw_dir;
  wire               yaw_pwm_enable;

  SPI spi_comm(
    .clk(clk),
    .spi_clk(SPI_CLK),
    .spi_pico(SPI_PICO),
    .spi_cs(SPI_CS),
    .spi_poci(SPI_POCI),

    .pitch_encoder_count(pitch_count),
    .pitch_pwm_duty(pitch_pwm_duty),
    .pitch_dir(pitch_dir),
    .pitch_pwm_enable(pitch_pwm_enable),

    .yaw_encoder_count(yaw_count),
    .yaw_pwm_duty(yaw_pwm_duty),
    .yaw_dir(yaw_dir),
    .yaw_pwm_enable(yaw_pwm_enable)
  );

  QuadDecoder pitch_decoder (
    .clk(clk),
    .A(PITCH_ENC_A),
    .B(PITCH_ENC_B),
    .rst(btn1),
    .count(pitch_count)
  );

  PWM pitch_pwm (
    .clk(clk),
    .rst(btn1),
    .enable(pitch_pwm_enable),
    .dir(pitch_dir),
    .duty(pitch_pwm_duty),
    .INA(PITCH_DIRA),
    .INB(PITCH_DIRB),
    .C(PITCH_PWM_VAL)
  );

  QuadDecoder yaw_decoder (
    .clk(clk),
    .A(YAW_ENC_A),
    .B(YAW_ENC_B),
    .rst(btn1),
    .count(yaw_count)
  );

  PWM yaw_pwm (
    .clk(clk),
    .rst(btn1),
    .enable(yaw_pwm_enable),
    .dir(yaw_dir),
    .duty(yaw_pwm_duty),
    .INA(YAW_DIRA),
    .INB(YAW_DIRB),
    .C(YAW_PWM_VAL)
  );

endmodule

lab13-20simcontroller/RPI-controller/verilog/TopEntity_tb.v
`timescale 1 ns / 1 ps

module TopEntity_tb;

  // System clock and reset button
  reg clk = 0;
  reg btn1 = 1;  // active-high reset

  // SPI signals (master side)
  reg  SPI_CLK = 0;
  reg  SPI_CS = 1;   // active low
  reg  SPI_PICO = 0;   // MOSI
  wire SPI_POCI;       // MISO

  // For SPI transactions
  reg [31:0] rx_word;
  reg [15:0] yaw_cmd;
  reg [15:0] pitch_cmd;

  // Encoder inputs
  reg PITCH_ENC_A = 0, PITCH_ENC_B = 0;
  reg YAW_ENC_A = 0, YAW_ENC_B = 0;

  // PWM outputs
  wire PITCH_DIRA, PITCH_DIRB, PITCH_PWM_VAL;
  wire YAW_DIRA,   YAW_DIRB,   YAW_PWM_VAL;

  // Generate main 50 MHz system clock (20 ns period)
  always #10 clk = ~clk;

  // Generate SPI clock (2 MHz -> 250 ns period)
  always #125 SPI_CLK = ~SPI_CLK;

  // Instantiate DUT
  TopEntity dut (
    .clk          (clk),
    .btn1         (btn1),

    .SPI_CLK      (SPI_CLK),
    .SPI_PICO     (SPI_PICO),
    .SPI_CS       (SPI_CS),

    .PITCH_ENC_A  (PITCH_ENC_A),
    .PITCH_ENC_B  (PITCH_ENC_B),

    .YAW_ENC_A    (YAW_ENC_A),
    .YAW_ENC_B    (YAW_ENC_B),

    .PITCH_DIRA   (PITCH_DIRA),
    .PITCH_PWM_VAL(PITCH_PWM_VAL),
    .PITCH_DIRB   (PITCH_DIRB),

    .YAW_DIRA     (YAW_DIRA),
    .YAW_PWM_VAL  (YAW_PWM_VAL),
    .YAW_DIRB     (YAW_DIRB),

    .SPI_POCI     (SPI_POCI)
  );

  // SPI mode 0, 32-bit transfer
  task spi_transfer32(
    input  [31:0] mosi_word,
    output [31:0] miso_word
  );
    integer i;
    reg [31:0] miso_tmp;
    begin
      miso_tmp = 0;
      // Wait for a known falling edge to align phase
      @(negedge SPI_CLK);
      // Start transaction: CS low
      SPI_CS = 0;

      // SPI_CLK is already toggling in its own always block
      for (i = 31; i >= 0; i = i - 1) begin
        // Put MOSI bit on line before rising edge
        SPI_PICO = mosi_word[i];

         // Wait for rising edge: master samples MISO, slave samples MOSI
        @(posedge SPI_CLK);
        miso_tmp[i] = SPI_POCI;

        // Wait for falling edge, where slave will shift next bit
        @(negedge SPI_CLK);
      end

      // End transaction
      SPI_CS = 1;
      SPI_PICO = 0;
      miso_word = miso_tmp;
      #500;
    end
  endtask

  initial begin
    // Optional waves
    $dumpfile("TopEntity_tb.vcd");
    $dumpvars(0, TopEntity_tb);

    // Reset
    btn1 = 1;
    #200;
    // Adding Initial values
    SPI_CS = 1;
    SPI_PICO = 0;
    PITCH_ENC_A = 0;
    PITCH_ENC_B = 0;
    YAW_ENC_A = 0;
    YAW_ENC_B = 0;
    btn1 = 0;
    #600;

    // Move pitch encoder forward: 00 -> 10 -> 11 -> 01 -> 00
    PITCH_ENC_A = 0; PITCH_ENC_B = 0; #500;
    PITCH_ENC_A = 1; PITCH_ENC_B = 0; #500;
    PITCH_ENC_A = 1; PITCH_ENC_B = 1; #500;
    PITCH_ENC_A = 0; PITCH_ENC_B = 1; #500;
    PITCH_ENC_A = 0; PITCH_ENC_B = 0; #500;
    // Move one back
    PITCH_ENC_A = 0; PITCH_ENC_B = 1; #500;
    $display("T=%0t pitch count=%0d", $time, dut.pitch_decoder.count);

    // Move yaw encoder backward: 00 -> 10 -> 11 -> 01 -> 00
    YAW_ENC_A = 0; YAW_ENC_B = 0; #500;
    YAW_ENC_A = 0; YAW_ENC_B = 1; #500;
    YAW_ENC_A = 1; YAW_ENC_B = 1; #500;
    YAW_ENC_A = 1; YAW_ENC_B = 0; #500;
    YAW_ENC_A = 0; YAW_ENC_B = 0; #500;
    // Move one forward
    YAW_ENC_A = 1; YAW_ENC_B = 0; #500;
    $display("T=%0t yaw count=%0d", $time, dut.yaw_decoder.count);

    // Read encoder via SPI (send 0 as command)
    spi_transfer32(0, rx_word);
    $display("T=%0t SPI read: pitch=%0d yaw=%0d", $time, $signed(rx_word[15:0]), $signed(rx_word[31:16]));

    // Wait a bit
    #500;

    // Build a motor command
    yaw_cmd   = {1'b1, 1'b1, 14'd1000}; // yaw: dir=1, enable=1, duty=1000
    pitch_cmd = {1'b0, 1'b1, 14'd500};  // pitch: dir=0, enable=1, duty=500

    spi_transfer32({yaw_cmd, pitch_cmd}, rx_word);
    $display("T=%0t Received motor control values: pitch_dir=%b pitch_enable=%b pitch_duty=%d | yaw_dir=%b yaw_enable=%b yaw_duty=%d",
      $time,
      dut.pitch_dir, dut.pitch_pwm_enable, dut.pitch_pwm_duty,
      dut.yaw_dir,   dut.yaw_pwm_enable,   dut.yaw_pwm_duty
    );
    $display("T=%0t PWM values: pitch: INA=%b INB=%b | yaw: INA=%b INB=%b",
      $time,
      dut.PITCH_DIRA, dut.PITCH_DIRB,
      dut.YAW_DIRA, dut.YAW_DIRB,
    );

    #200000;
    $finish;
  end

endmodule

lab13-20simcontroller/RPI-controller/verilog/TopEntity_tb.vcd
$date
	Tue May 26 18:14:44 2026
$end
$version
	Icarus Verilog
$end
$timescale
	1ps
$end
$scope module TopEntity_tb $end
$var wire 1 ! YAW_PWM_VAL $end
$var wire 1 " YAW_DIRB $end
$var wire 1 # YAW_DIRA $end
$var wire 1 $ SPI_POCI $end
$var wire 1 % PITCH_PWM_VAL $end
$var wire 1 & PITCH_DIRB $end
$var wire 1 ' PITCH_DIRA $end
$var reg 1 ( PITCH_ENC_A $end
$var reg 1 ) PITCH_ENC_B $end
$var reg 1 * SPI_CLK $end
$var reg 1 + SPI_CS $end
$var reg 1 , SPI_PICO $end
$var reg 1 - YAW_ENC_A $end
$var reg 1 . YAW_ENC_B $end
$var reg 1 / btn1 $end
$var reg 1 0 clk $end
$var reg 16 1 pitch_cmd [15:0] $end
$var reg 32 2 rx_word [31:0] $end
$var reg 16 3 yaw_cmd [15:0] $end
$scope module dut $end
$var wire 1 ( PITCH_ENC_A $end
$var wire 1 ) PITCH_ENC_B $end
$var wire 1 * SPI_CLK $end
$var wire 1 + SPI_CS $end
$var wire 1 , SPI_PICO $end
$var wire 1 - YAW_ENC_A $end
$var wire 1 . YAW_ENC_B $end
$var wire 1 / btn1 $end
$var wire 1 0 clk $end
$var wire 1 4 yaw_pwm_enable $end
$var wire 14 5 yaw_pwm_duty [13:0] $end
$var wire 1 6 yaw_dir $end
$var wire 16 7 yaw_count [15:0] $end
$var wire 1 8 pitch_pwm_enable $end
$var wire 14 9 pitch_pwm_duty [13:0] $end
$var wire 1 : pitch_dir $end
$var wire 16 ; pitch_count [15:0] $end
$var wire 1 ! YAW_PWM_VAL $end
$var wire 1 " YAW_DIRB $end
$var wire 1 # YAW_DIRA $end
$var wire 1 $ SPI_POCI $end
$var wire 1 % PITCH_PWM_VAL $end
$var wire 1 & PITCH_DIRB $end
$var wire 1 ' PITCH_DIRA $end
$scope module pitch_decoder $end
$var wire 1 ( A $end
$var wire 1 ) B $end
$var wire 1 0 clk $end
$var wire 1 / rst $end
$var parameter 2 < S00 $end
$var parameter 2 = S01 $end
$var parameter 2 > S10 $end
$var parameter 2 ? S11 $end
$var reg 2 @ AB [1:0] $end
$var reg 16 A count [15:0] $end
$var reg 2 B state [1:0] $end
$var reg 2 C sync [1:0] $end
$upscope $end
$scope module pitch_pwm $end
$var wire 1 0 clk $end
$var wire 1 / rst $end
$var wire 1 8 enable $end
$var wire 14 D duty [13:0] $end
$var wire 1 : dir $end
$var parameter 32 E CLK_FREQ $end
$var parameter 32 F PWM_FREQ $end
$var parameter 32 G PWM_PERIOD $end
$var reg 1 % C $end
$var reg 1 ' INA $end
$var reg 1 & INB $end
$var reg 14 H counter [13:0] $end
$upscope $end
$scope module spi_comm $end
$var wire 1 0 clk $end
$var wire 1 : pitch_dir $end
$var wire 16 I pitch_encoder_count [15:0] $end
$var wire 14 J pitch_pwm_duty [13:0] $end
$var wire 1 8 pitch_pwm_enable $end
$var wire 1 / rst $end
$var wire 1 * spi_clk $end
$var wire 1 + spi_cs $end
$var wire 1 , spi_pico $end
$var wire 1 6 yaw_dir $end
$var wire 14 K yaw_pwm_duty [13:0] $end
$var wire 1 4 yaw_pwm_enable $end
$var wire 16 L yaw_encoder_count [15:0] $end
$var wire 1 $ spi_poci $end
$var reg 6 M bit_count [5:0] $end
$var reg 1 N pitch_dir_r $end
$var reg 14 O pitch_pwm_duty_r [13:0] $end
$var reg 1 P pitch_pwm_enable_r $end
$var reg 32 Q rx_shift [31:0] $end
$var reg 32 R tx_shift [31:0] $end
$var reg 1 S yaw_dir_r $end
$var reg 14 T yaw_pwm_duty_r [13:0] $end
$var reg 1 U yaw_pwm_enable_r $end
$upscope $end
$scope module yaw_decoder $end
$var wire 1 - A $end
$var wire 1 . B $end
$var wire 1 0 clk $end
$var wire 1 / rst $end
$var parameter 2 V S00 $end
$var parameter 2 W S01 $end
$var parameter 2 X S10 $end
$var parameter 2 Y S11 $end
$var reg 2 Z AB [1:0] $end
$var reg 16 [ count [15:0] $end
$var reg 2 \ state [1:0] $end
$var reg 2 ] sync [1:0] $end
$upscope $end
$scope module yaw_pwm $end
$var wire 1 0 clk $end
$var wire 1 6 dir $end
$var wire 14 ^ duty [13:0] $end
$var wire 1 4 enable $end
$var wire 1 / rst $end
$var parameter 32 _ CLK_FREQ $end
$var parameter 32 ` PWM_FREQ $end
$var parameter 32 a PWM_PERIOD $end
$var reg 1 ! C $end
$var reg 1 # INA $end
$var reg 1 " INB $end
$var reg 14 b counter [13:0] $end
$upscope $end
$upscope $end
$scope task spi_transfer32 $end
$var reg 32 c miso_tmp [31:0] $end
$var reg 32 d miso_word [31:0] $end
$var reg 32 e mosi_word [31:0] $end
$var integer 32 f i [31:0] $end
$upscope $end
$upscope $end
$enddefinitions $end
$comment Show the parameter values. $end
$dumpall
b100111000100 a
b100111000100000 `
b10111110101111000010000000 _
b11 Y
b10 X
b1 W
b0 V
b100111000100 G
b100111000100000 F
b10111110101111000010000000 E
b11 ?
b10 >
b1 =
b0 <
$end
#0
$dumpvars
bx f
bx e
bx d
bx c
b0 b
b0 ^
b0 ]
b0 \
bx [
b0 Z
0U
b0 T
0S
b0 R
b0 Q
0P
b0 O
0N
b0 M
bx L
b0 K
b0 J
bx I
b0 H
b0 D
b0 C
b0 B
bx A
b0 @
bx ;
0:
b0 9
08
bx 7
06
b0 5
04
bx 3
bx 2
bx 1
00
1/
0.
0-
0,
1+
0*
0)
0(
0'
0&
0%
0$
0#
0"
0!
$end
#10000
b0 ;
b0 A
b0 I
b0 7
b0 L
b0 [
10
#20000
00
#30000
10
#40000
00
#50000
10
#60000
00
#70000
10
#80000
00
#90000
10
#100000
00
#110000
10
#120000
00
#125000
1*
#130000
10
#140000
00
#150000
10
#160000
00
#170000
10
#180000
00
#190000
10
#200000
00
0/
#210000
b1 b
b1 H
10
#220000
00
#230000
b10 H
b10 b
10
#240000
00
#250000
b11 b
b11 H
10
0*
#260000
00
#270000
b100 H
b100 b
10
#280000
00
#290000
b101 b
b101 H
10
#300000
00
#310000
b110 H
b110 b
10
#320000
00
#330000
b111 b
b111 H
10
#340000
00
#350000
b1000 H
b1000 b
10
#360000
00
#370000
b1001 b
b1001 H
10
#375000
1*
#380000
00
#390000
b1010 H
b1010 b
10
#400000
00
#410000
b1011 b
b1011 H
10
#420000
00
#430000
b1100 H
b1100 b
10
#440000
00
#450000
b1101 b
b1101 H
10
#460000
00
#470000
b1110 H
b1110 b
10
#480000
00
#490000
b1111 b
b1111 H
10
#500000
00
0*
#510000
b10000 H
b10000 b
10
#520000
00
#530000
b10001 b
b10001 H
10
#540000
00
#550000
b10010 H
b10010 b
10
#560000
00
#570000
b10011 b
b10011 H
10
#580000
00
#590000
b10100 H
b10100 b
10
#600000
00
#610000
b10101 b
b10101 H
10
#620000
00
#625000
1*
#630000
b10110 H
b10110 b
10
#640000
00
#650000
b10111 b
b10111 H
10
#660000
00
#670000
b11000 H
b11000 b
10
#680000
00
#690000
b11001 b
b11001 H
10
#700000
00
#710000
b11010 H
b11010 b
10
#720000
00
#730000
b11011 b
b11011 H
10
#740000
00
#750000
b11100 H
b11100 b
10
0*
#760000
00
#770000
b11101 b
b11101 H
10
#780000
00
#790000
b11110 H
b11110 b
10
#800000
00
#810000
b11111 b
b11111 H
10
#820000
00
#830000
b100000 H
b100000 b
10
#840000
00
#850000
b100001 b
b100001 H
10
#860000
00
#870000
b100010 H
b100010 b
10
#875000
1*
#880000
00
#890000
b100011 b
b100011 H
10
#900000
00
#910000
b100100 H
b100100 b
10
#920000
00
#930000
b100101 b
b100101 H
10
#940000
00
#950000
b100110 H
b100110 b
10
#960000
00
#970000
b100111 b
b100111 H
10
#980000
00
#990000
b101000 H
b101000 b
10
#1000000
00
0*
#1010000
b101001 b
b101001 H
10
#1020000
00
#1030000
b101010 H
b101010 b
10
#1040000
00
#1050000
b101011 b
b101011 H
10
#1060000
00
#1070000
b101100 H
b101100 b
10
#1080000
00
#1090000
b101101 b
b101101 H
10
#1100000
00
#1110000
b101110 H
b101110 b
10
#1120000
00
#1125000
1*
#1130000
b101111 b
b101111 H
10
#1140000
00
#1150000
b110000 H
b110000 b
10
#1160000
00
#1170000
b110001 b
b110001 H
10
#1180000
00
#1190000
b110010 H
b110010 b
10
#1200000
00
#1210000
b110011 b
b110011 H
10
#1220000
00
#1230000
b110100 H
b110100 b
10
#1240000
00
#1250000
b110101 b
b110101 H
10
0*
#1260000
00
#1270000
b110110 H
b110110 b
10
#1280000
00
#1290000
b110111 b
b110111 H
10
#1300000
00
1(
#1310000
b10 C
b111000 H
b111000 b
10
#1320000
00
#1330000
b10 @
b111001 b
b111001 H
10
#1340000
00
#1350000
b10 B
b1 ;
b1 A
b1 I
b111010 H
b111010 b
10
#1360000
00
#1370000
b111011 b
b111011 H
10
#1375000
1*
#1380000
00
#1390000
b111100 H
b111100 b
10
#1400000
00
#1410000
b111101 b
b111101 H
10
#1420000
00
#1430000
b111110 H
b111110 b
10
#1440000
00
#1450000
b111111 b
b111111 H
10
#1460000
00
#1470000
b1000000 H
b1000000 b
10
#1480000
00
#1490000
b1000001 b
b1000001 H
10
#1500000
00
0*
#1510000
b1000010 H
b1000010 b
10
#1520000
00
#1530000
b1000011 b
b1000011 H
10
#1540000
00
#1550000
b1000100 H
b1000100 b
10
#1560000
00
#1570000
b1000101 b
b1000101 H
10
#1580000
00
#1590000
b1000110 H
b1000110 b
10
#1600000
00
#1610000
b1000111 b
b1000111 H
10
#1620000
00
#1625000
1*
#1630000
b1001000 H
b1001000 b
10
#1640000
00
#1650000
b1001001 b
b1001001 H
10
#1660000
00
#1670000
b1001010 H
b1001010 b
10
#1680000
00
#1690000
b1001011 b
b1001011 H
10
#1700000
00
#1710000
b1001100 H
b1001100 b
10
#1720000
00
#1730000
b1001101 b
b1001101 H
10
#1740000
00
#1750000
b1001110 H
b1001110 b
10
0*
#1760000
00
#1770000
b1001111 b
b1001111 H
10
#1780000
00
#1790000
b1010000 H
b1010000 b
10
#1800000
00
1)
#1810000
b11 C
b1010001 b
b1010001 H
10
#1820000
00
#1830000
b11 @
b1010010 H
b1010010 b
10
#1840000
00
#1850000
b11 B
b10 ;
b10 A
b10 I
b1010011 b
b1010011 H
10
#1860000
00
#1870000
b1010100 H
b1010100 b
10
#1875000
1*
#1880000
00
#1890000
b1010101 b
b1010101 H
10
#1900000
00
#1910000
b1010110 H
b1010110 b
10
#1920000
00
#1930000
b1010111 b
b1010111 H
10
#1940000
00
#1950000
b1011000 H
b1011000 b
10
#1960000
00
#1970000
b1011001 b
b1011001 H
10
#1980000
00
#1990000
b1011010 H
b1011010 b
10
#2000000
00
0*
#2010000
b1011011 b
b1011011 H
10
#2020000
00
#2030000
b1011100 H
b1011100 b
10
#2040000
00
#2050000
b1011101 b
b1011101 H
10
#2060000
00
#2070000
b1011110 H
b1011110 b
10
#2080000
00
#2090000
b1011111 b
b1011111 H
10
#2100000
00
#2110000
b1100000 H
b1100000 b
10
#2120000
00
#2125000
1*
#2130000
b1100001 b
b1100001 H
10
#2140000
00
#2150000
b1100010 H
b1100010 b
10
#2160000
00
#2170000
b1100011 b
b1100011 H
10
#2180000
00
#2190000
b1100100 H
b1100100 b
10
#2200000
00
#2210000
b1100101 b
b1100101 H
10
#2220000
00
#2230000
b1100110 H
b1100110 b
10
#2240000
00
#2250000
b1100111 b
b1100111 H
10
0*
#2260000
00
#2270000
b1101000 H
b1101000 b
10
#2280000
00
#2290000
b1101001 b
b1101001 H
10
#2300000
00
0(
#2310000
b1 C
b1101010 H
b1101010 b
10
#2320000
00
#2330000
b1 @
b1101011 b
b1101011 H
10
#2340000
00
#2350000
b1 B
b11 ;
b11 A
b11 I
b1101100 H
b1101100 b
10
#2360000
00
#2370000
b1101101 b
b1101101 H
10
#2375000
1*
#2380000
00
#2390000
b1101110 H
b1101110 b
10
#2400000
00
#2410000
b1101111 b
b1101111 H
10
#2420000
00
#2430000
b1110000 H
b1110000 b
10
#2440000
00
#2450000
b1110001 b
b1110001 H
10
#2460000
00
#2470000
b1110010 H
b1110010 b
10
#2480000
00
#2490000
b1110011 b
b1110011 H
10
#2500000
00
0*
#2510000
b1110100 H
b1110100 b
10
#2520000
00
#2530000
b1110101 b
b1110101 H
10
#2540000
00
#2550000
b1110110 H
b1110110 b
10
#2560000
00
#2570000
b1110111 b
b1110111 H
10
#2580000
00
#2590000
b1111000 H
b1111000 b
10
#2600000
00
#2610000
b1111001 b
b1111001 H
10
#2620000
00
#2625000
1*
#2630000
b1111010 H
b1111010 b
10
#2640000
00
#2650000
b1111011 b
b1111011 H
10
#2660000
00
#2670000
b1111100 H
b1111100 b
10
#2680000
00
#2690000
b1111101 b
b1111101 H
10
#2700000
00
#2710000
b1111110 H
b1111110 b
10
#2720000
00
#2730000
b1111111 b
b1111111 H
10
#2740000
00
#2750000
b10000000 H
b10000000 b
10
0*
#2760000
00
#2770000
b10000001 b
b10000001 H
10
#2780000
00
#2790000
b10000010 H
b10000010 b
10
#2800000
00
0)
#2810000
b0 C
b10000011 b
b10000011 H
10
#2820000
00
#2830000
b0 @
b10000100 H
b10000100 b
10
#2840000
00
#2850000
b0 B
b100 ;
b100 A
b100 I
b10000101 b
b10000101 H
10
#2860000
00
#2870000
b10000110 H
b10000110 b
10
#2875000
1*
#2880000
00
#2890000
b10000111 b
b10000111 H
10
#2900000
00
#2910000
b10001000 H
b10001000 b
10
#2920000
00
#2930000
b10001001 b
b10001001 H
10
#2940000
00
#2950000
b10001010 H
b10001010 b
10
#2960000
00
#2970000
b10001011 b
b10001011 H
10
#2980000
00
#2990000
b10001100 H
b10001100 b
10
#3000000
00
0*
#3010000
b10001101 b
b10001101 H
10
#3020000
00
#3030000
b10001110 H
b10001110 b
10
#3040000
00
#3050000
b10001111 b
b10001111 H
10
#3060000
00
#3070000
b10010000 H
b10010000 b
10
#3080000
00
#3090000
b10010001 b
b10010001 H
10
#3100000
00
#3110000
b10010010 H
b10010010 b
10
#3120000
00
#3125000
1*
#3130000
b10010011 b
b10010011 H
10
#3140000
00
#3150000
b10010100 H
b10010100 b
10
#3160000
00
#3170000
b10010101 b
b10010101 H
10
#3180000
00
#3190000
b10010110 H
b10010110 b
10
#3200000
00
#3210000
b10010111 b
b10010111 H
10
#3220000
00
#3230000
b10011000 H
b10011000 b
10
#3240000
00
#3250000
b10011001 b
b10011001 H
10
0*
#3260000
00
#3270000
b10011010 H
b10011010 b
10
#3280000
00
#3290000
b10011011 b
b10011011 H
10
#3300000
00
1)
#3310000
b1 C
b10011100 H
b10011100 b
10
#3320000
00
#3330000
b1 @
b10011101 b
b10011101 H
10
#3340000
00
#3350000
b1 B
b11 ;
b11 A
b11 I
b10011110 H
b10011110 b
10
#3360000
00
#3370000
b10011111 b
b10011111 H
10
#3375000
1*
#3380000
00
#3390000
b10100000 H
b10100000 b
10
#3400000
00
#3410000
b10100001 b
b10100001 H
10
#3420000
00
#3430000
b10100010 H
b10100010 b
10
#3440000
00
#3450000
b10100011 b
b10100011 H
10
#3460000
00
#3470000
b10100100 H
b10100100 b
10
#3480000
00
#3490000
b10100101 b
b10100101 H
10
#3500000
00
0*
#3510000
b10100110 H
b10100110 b
10
#3520000
00
#3530000
b10100111 b
b10100111 H
10
#3540000
00
#3550000
b10101000 H
b10101000 b
10
#3560000
00
#3570000
b10101001 b
b10101001 H
10
#3580000
00
#3590000
b10101010 H
b10101010 b
10
#3600000
00
#3610000
b10101011 b
b10101011 H
10
#3620000
00
#3625000
1*
#3630000
b10101100 H
b10101100 b
10
#3640000
00
#3650000
b10101101 b
b10101101 H
10
#3660000
00
#3670000
b10101110 H
b10101110 b
10
#3680000
00
#3690000
b10101111 b
b10101111 H
10
#3700000
00
#3710000
b10110000 H
b10110000 b
10
#3720000
00
#3730000
b10110001 b
b10110001 H
10
#3740000
00
#3750000
b10110010 H
b10110010 b
10
0*
#3760000
00
#3770000
b10110011 b
b10110011 H
10
#3780000
00
#3790000
b10110100 H
b10110100 b
10
#3800000
00
#3810000
b10110101 b
b10110101 H
10
#3820000
00
#3830000
b10110110 H
b10110110 b
10
#3840000
00
#3850000
b10110111 b
b10110111 H
10
#3860000
00
#3870000
b10111000 H
b10111000 b
10
#3875000
1*
#3880000
00
#3890000
b10111001 b
b10111001 H
10
#3900000
00
#3910000
b10111010 H
b10111010 b
10
#3920000
00
#3930000
b10111011 b
b10111011 H
10
#3940000
00
#3950000
b10111100 H
b10111100 b
10
#3960000
00
#3970000
b10111101 b
b10111101 H
10
#3980000
00
#3990000
b10111110 H
b10111110 b
10
